docs/Makefile
docs/changelog.rst
docs/conf.py
docs/index.rst
docs/requirements.txt
docs/api/index.rst
docs/contributing/index.rst
scrapyloganalyzer/__init__.py
scrapyloganalyzer-0.0.5.dist-info/LICENSE
scrapyloganalyzer-0.0.5.dist-info/METADATA
scrapyloganalyzer-0.0.5.dist-info/WHEEL
scrapyloganalyzer-0.0.5.dist-info/top_level.txt
scrapyloganalyzer-0.0.5.dist-info/RECORD
