Metadata-Version: 2.2
Name: scrapyloganalyzer
Version: 0.0.5
Summary: Provides methods to analyze the quality of a Scrapy crawl.
Author-email: Open Contracting Partnership <data@open-contracting.org>
License: BSD
Project-URL: Homepage, https://github.com/open-contracting/scrapy-log-analyzer
Classifier: License :: OSI Approved :: BSD License
Classifier: Operating System :: OS Independent
Classifier: Programming Language :: Python :: 3.9
Classifier: Programming Language :: Python :: 3.10
Classifier: Programming Language :: Python :: 3.11
Classifier: Programming Language :: Python :: 3.12
Classifier: Programming Language :: Python :: Implementation :: CPython
Classifier: Programming Language :: Python :: Implementation :: PyPy
License-File: LICENSE
Requires-Dist: logparser
Provides-Extra: test
Requires-Dist: coverage; extra == "test"
Requires-Dist: pytest; extra == "test"
